dbshiftSDK/__init__.py
dbshiftSDK-1.0.3.dist-info/LICENSE.txt
dbshiftSDK-1.0.3.dist-info/METADATA
dbshiftSDK-1.0.3.dist-info/WHEEL
dbshiftSDK-1.0.3.dist-info/top_level.txt
dbshiftSDK-1.0.3.dist-info/RECORD
