Metadata-Version: 2.1
Name: dbshiftSDK
Version: 1.0.3
Summary: A tool for converting Informatica XML mappings to Snowflake SQL and dbt models.
Author: Anand
Author-email: anandt@systechusa.com
Classifier: Programming Language :: Python :: 3
Classifier: License :: OSI Approved :: MIT License
Classifier: Operating System :: OS Independent
License-File: LICENSE.txt
Requires-Dist: google-generativeai
Requires-Dist: tabulate
Requires-Dist: argparse
